surquest/utils/requirements.txt
surquest/utils/scrappers/tesco/__init__.py
surquest/utils/scrappers/tesco/facets.py
surquest/utils/scrappers/tesco/graphql.product.gql
surquest/utils/scrappers/tesco/graphql.products.gql
surquest/utils/scrappers/tesco/graphql.taxonomy.gql
surquest/utils/scrappers/tesco/handler.py
surquest/utils/scrappers/tesco/scrapper.py
surquest_utils_scrappers_grocery-0.0.1rc2.dist-info/METADATA
surquest_utils_scrappers_grocery-0.0.1rc2.dist-info/WHEEL
surquest_utils_scrappers_grocery-0.0.1rc2.dist-info/licenses/LICENSE
surquest_utils_scrappers_grocery-0.0.1rc2.dist-info/RECORD
