Metadata-Version: 2.4
Name: surquest-utils-scrappers-grocery
Version: 0.0.1rc2
Summary: A collection of web scrapers designed to extract grocery product data from grocery retailers
Project-URL: Homepage, https://github.com/surquest/python-grocery-products-scrapper
Project-URL: Bug Tracker, https://github.com/surquest/python-grocery-products-scrapper/issues
Author-email: Michal Švarc <michal.svarc@surquest.com>
License-File: LICENSE
Requires-Dist: requests<3.0,>=2.32.4
Provides-Extra: test
Requires-Dist: pytest-cov==6.2.1; extra == 'test'
Requires-Dist: pytest==8.4.1; extra == 'test'
